amber_mcap/__init__.py
amber_mcap/apps/image_search.py
amber_mcap/automation/annotation.py
amber_mcap/automation/automation.py
amber_mcap/automation/blip2_encoder.py
amber_mcap/automation/clip_encoder.py
amber_mcap/automation/clip_image_annotation_filter.py
amber_mcap/automation/detic_image_labeler.py
amber_mcap/automation/nerf_3d_reconstruction.py
amber_mcap/automation/onnx/.gitignore
amber_mcap/automation/sentence_transformer.py
amber_mcap/automation/task_description.py
amber_mcap/cli.py
amber_mcap/dataset/conversion.py
amber_mcap/dataset/images_and_annotations_dataset.py
amber_mcap/dataset/images_dataset.py
amber_mcap/dataset/pointcloud_dataset.py
amber_mcap/dataset/rosbag2_dataset.py
amber_mcap/dataset/schema.py
amber_mcap/dataset/tf_dataset.py
amber_mcap/dataset/topic_config.py
amber_mcap/exception.py
amber_mcap/importer/tf.py
amber_mcap/importer/video.py
amber_mcap/tf2/console_bridge/include/console_bridge/console.h
amber_mcap/tf2/console_bridge/src/console.cpp
amber_mcap/tf2/geometry2/tf2/include/tf2/LinearMath/Matrix3x3.h
amber_mcap/tf2/geometry2/tf2/include/tf2/LinearMath/MinMax.h
amber_mcap/tf2/geometry2/tf2/include/tf2/LinearMath/QuadWord.h
amber_mcap/tf2/geometry2/tf2/include/tf2/LinearMath/Quaternion.h
amber_mcap/tf2/geometry2/tf2/include/tf2/LinearMath/Scalar.h
amber_mcap/tf2/geometry2/tf2/include/tf2/LinearMath/Transform.h
amber_mcap/tf2/geometry2/tf2/include/tf2/LinearMath/Vector3.h
amber_mcap/tf2/geometry2/tf2/include/tf2/buffer_core.h
amber_mcap/tf2/geometry2/tf2/include/tf2/buffer_core_interface.h
amber_mcap/tf2/geometry2/tf2/include/tf2/convert.h
amber_mcap/tf2/geometry2/tf2/include/tf2/exceptions.h
amber_mcap/tf2/geometry2/tf2/include/tf2/impl/convert.h
amber_mcap/tf2/geometry2/tf2/include/tf2/impl/utils.h
amber_mcap/tf2/geometry2/tf2/include/tf2/time.h
amber_mcap/tf2/geometry2/tf2/include/tf2/time_cache.h
amber_mcap/tf2/geometry2/tf2/include/tf2/transform_datatypes.h
amber_mcap/tf2/geometry2/tf2/include/tf2/transform_storage.h
amber_mcap-0.6.0.dist-info/LICENSE
amber_mcap-0.6.0.dist-info/METADATA
amber_mcap-0.6.0.dist-info/WHEEL
amber_mcap-0.6.0.dist-info/entry_points.txt
amber_mcap-0.6.0.dist-info/RECORD
