Metadata-Version: 2.3
Name: amber_mcap
Version: 0.6.0
Summary: Annotation and Multimodal Bag Extraction for Robotics
License: Apache 2.0
Author: Masaya Kataoka
Author-email: ms.kataoka@gmail.com
Requires-Python: >=3.10,<3.13
Classifier: License :: Other/Proprietary License
Classifier: Programming Language :: Python :: 3
Classifier: Programming Language :: Python :: 3.10
Classifier: Programming Language :: Python :: 3.11
Classifier: Programming Language :: Python :: 3.12
Requires-Dist: Pillow (>=9.2.0,<11.0)
Requires-Dist: addict (>=2.4.0,<3.0.0)
Requires-Dist: boto3 (>=1.20.0,<2.0.0)
Requires-Dist: dataclass-wizard (>=0.22.2,<0.23.0)
Requires-Dist: datetime (>=5.3,<6.0)
Requires-Dist: docker (>=6.1.2,<7.0.0)
Requires-Dist: download (>=0.3.5,<0.4.0)
Requires-Dist: ftfy (>=6.1.1,<7.0.0)
Requires-Dist: huggingface-hub (>=0.30.2,<0.31.0)
Requires-Dist: mcap-ros2-support (>=0.3.0,<0.4.0)
Requires-Dist: numpy (==1.26.4)
Requires-Dist: numpy-quaternion (>=2024.0.8,<2025.0.0)
Requires-Dist: onnxruntime-gpu (>=1.15.1,<2.0.0)
Requires-Dist: open3d (>=0.18.0,<0.19.0)
Requires-Dist: opencv-python (>=4.11.0.86,<5.0.0.0)
Requires-Dist: pandas (>=2.0.3,<3.0.0)
Requires-Dist: pybind11 (>=2.13.6,<3.0.0)
Requires-Dist: pyparsing
Requires-Dist: pyyaml (>=6.0.0,<7.0.0)
Requires-Dist: pyzstd (>=0.16.2,<0.17.0)
Requires-Dist: regex (>=2023.3.23,<2024.0.0)
Requires-Dist: scikit-learn (>=1.6.0,<2.0.0)
Requires-Dist: scipy (>=1.9.0,<2.0.0)
Requires-Dist: sentence-transformers (>=2.2.2,<3.0.0)
Requires-Dist: setuptools (==58.2.0)
Requires-Dist: tensorboard (>=2.14.0,<3.0.0)
Requires-Dist: tensorboardx (>=2.6.2.2,<3.0.0.0)
Requires-Dist: threadpoolctl (>=3.2.0,<4.0.0)
Requires-Dist: torch (==2.5.0+cu124)
Requires-Dist: torchaudio (==2.5.0+cu124)
Requires-Dist: torchvision (==0.20.0+cu124)
Requires-Dist: transformers (>=4.51.3,<5.0.0)
Requires-Dist: urllib3 (>=1.26.0,<2.0.0)
